Workbook
Name aporte: Planilha1!$D$12
Name patrimonio: Planilha1!$D$15
Name qtd_anos: Planilha1!$D$13
Name rendimento_carteira: Planilha1!$D$5
Name salario: Planilha1!$D$4
Name sugestao_investimento: Planilha1!$D$6
Name taxa_mensal: Planilha1!$D$14

Sheet Planilha1
B3: CONFIGURAÇÕES
B4: Salário | D4: 3571.61
B5: Rendimento Carteira | D5: 0.006
B6: Sugestão investimento (30%) | D6: =D4*30% -> 1071.483
B8: INVESTIMENTO MENSAL
B12: Quanto investir por mês? | D12: 1071
B13: Por Quantos Anos? | D13: 2
B14: Taxa de Rendimento mensal? | D14: 0.0108
B15: Patrimônio acumulado? | D15: =FV(taxa_mensal,qtd_anos*12,aporte*-1) -> 29164.255
B16: Dividendos Mensais? | D16: =patrimonio*rendimento_carteira -> 174.98553
B18: CENÁRIOS | D18: Divideno
A19: 2 | B19: Quanto em 2 anos? | C19: =FV($D$14,$A19*12,$D$12*-1) -> 29164.255 | D19: =C19*rendimento_carteira -> 174.98553
A20: 5 | B20: Quanto em 5 anos? | C20: =FV($D$14,$A20*12,$D$12*-1) -> 89754.105 | D20: =C20*rendimento_carteira -> 538.52463
A21: 10 | B21: Quanto em 10 anos? | C21: =FV($D$14,$A21*12,$D$12*-1) -> 260743.16 | D21: =C21*rendimento_carteira -> 1564.459
A22: 20 | B22: Quanto em 20 anos? | C22: =FV($D$14,$A22*12,$D$12*-1) -> 1207069.5 | D22: =C22*rendimento_carteira -> 7242.4168
A23: 30 | B23: Quanto em 30 anos? | C23: =FV($D$14,$A23*12,$D$12*-1) -> 4641612.1 | D23: =C23*rendimento_carteira -> 27849.672
B25: Perfil | C25: Moderado
B26: VALOR A SER INVESTIDO POR MÊS | C26: =aporte -> 1071
B28: TIPO DE FII | C28: Percentual Sugerido | D28: Valores
B29: PAPEL | C29: =VLOOKUP($C$25&"-"&B29,Planilha2!$A:$D,4,FALSE) -> 0.32 | D29: =C29*$C$26 -> 342.72
B30: TIJOLO | C30: =VLOOKUP($C$25&"-"&B30,Planilha2!$A:$D,4,FALSE) -> 0.35 | D30: =C30*$C$26 -> 374.85
B31: HIBRIDOS | C31: =VLOOKUP($C$25&"-"&B31,Planilha2!$A:$D,4,FALSE) -> 0.08 | D31: =C31*$C$26 -> 85.68
B32: FOFs | C32: =VLOOKUP($C$25&"-"&B32,Planilha2!$A:$D,4,FALSE) -> 0.05 | D32: =C32*$C$26 -> 53.55
B33: DESENVOLVIMENTO | C33: =VLOOKUP($C$25&"-"&B33,Planilha2!$A:$D,4,FALSE) -> 0.1 | D33: =C33*$C$26 -> 107.1
B34: HOTELARIA | C34: =VLOOKUP($C$25&"-"&B34,Planilha2!$A:$D,4,FALSE) -> 10 | D34: =C34*$C$26 -> 10710
D35: =SUM(D29:D34) -> 11673.9

Sheet Planilha2
A2: CHAVE | B2: PERFIL | C2: TIPO DE FII | D2: %
A3: =Planilha1!C28+Planilha1!C28+Planilha1!C28 -> #VALUE! | B3: Conservador | C3: PAPEL | D3: 0.3 | G3: Moderado-TIJOLO | H3: =Planilha1!C29 -> 0.32
A4: =B4&"-"&C4 -> Conservador-TIJOLO | B4: Conservador | C4: TIJOLO | D4: 0.5
A5: =B5&"-"&C5 -> Conservador-HIBRIDOS | B5: Conservador | C5: HIBRIDOS | D5: 0.1
A6: =B6&"-"&C6 -> Conservador-FOFs | B6: Conservador | C6: FOFs | D6: 0.1
A7: =B7&"-"&C7 -> Conservador-DESENVOLVIMENTO | B7: Conservador | C7: DESENVOLVIMENTO | D7: 0
A8: =B8&"-"&C8 -> Conservador-HOTELARIA | B8: Conservador | C8: HOTELARIA | D8: 0
A9: =B9&"-"&C9 -> Moderado-PAPEL | B9: Moderado | C9: PAPEL | D9: 0.32
A10: =B10&"-"&C10 -> Moderado-TIJOLO | B10: Moderado | C10: TIJOLO | D10: 0.35
A11: =B11&"-"&C11 -> Moderado-HIBRIDOS | B11: Moderado | C11: HIBRIDOS | D11: 0.08
A12: =B12&"-"&C12 -> Moderado-FOFs | B12: Moderado | C12: FOFs | D12: 0.05
A13: =B13&"-"&C13 -> Moderado-DESENVOLVIMENTO | B13: Moderado | C13: DESENVOLVIMENTO | D13: 0.1
A14: =B14&"-"&C14 -> Moderado-HOTELARIA | B14: Moderado | C14: HOTELARIA | D14: 10
A15: =B15&"-"&C15 -> Agressivo-PAPEL | B15: Agressivo | C15: PAPEL | D15: 0.5
... A20: =B20&"-"&C20 -> Agressivo-HOTELARIA | B20: Agressivo | C20: HOTELARIA | D20: 0.1
